{"type":"files","data":[{"type":"file","data":{"id":"mewdtdjfmzkermq7","project_id":"perbzxnkfp28mjsr","label":"실습-recommendation","contents":{"mid":"mewdtdjfmzkermq7","type":"data","title":"실습-recommendation","functions":[{"persist-mode":"auto","func":"brightics.function.io$load13889","name":"brightics.function.io$load","param":{"partial_path":["/brightics@samsung.com/upload/30_Purchase_log.csv"]},"display":{"label":"Load","diagram":{"position":{"x":270,"y":20}},"sheet":{"out":{"partial":[{"panel":[{"id":"default-1734127884850","chartOption":{"colorSet":["#FD026C","#4682B8","#A5D22D","#F5CC0A","#FE8C01","#6B9494","#B97C46","#84ACD0","#C2E173","#F9DD5B","#FE569D","#FEB356","#9CB8B8","#D0A884","#2E6072","#6D8C1E","#A48806","#A90148","#A95E01","#476363","#7B532F"],"title":{"show":true,"text":"","subtext":"","rotate":0,"textStyle":{"color":"#000000","fontSize":12,"fontFamily":""},"subtextStyle":{"color":"#000000","fontSize":12,"fontFamily":""},"left":"50%","top":"0px"},"toolbar":{"show":false,"right":"8px","top":"8px","orientation":"horizontal","menu":{}},"chart":{"border":"1px #000000 none","background":"rgba(255, 255, 255,1)","animationDuration":1000,"type":"table"},"tooltip":{"triggerOn":"mousemove"},"grid":{"left":"10%","right":"10%","top":"60px","bottom":"60px","width":"auto","height":"auto"},"xAxis":[{"selected":[],"title":{"show":true,"text":"","subtext":"","rotate":0,"textStyle":{"color":"#000000","fontSize":12,"fontFamily":""},"subtextStyle":{"color":"#000000","fontSize":12,"fontFamily":""},"left":"50%","bottom":"5px"},"axisTick":{"show":true},"axisLine":{"onZero":false},"scale":true,"axisLabel":{"show":true,"rotate":0,"textStyle":{"color":"#000000","fontSize":12,"fontFamily":""},"interval":"auto"},"splitLine":{"show":false,"lineStyle":{"color":"#cccccc","width":1,"type":"solid"}},"zlevel":1}],"yAxis":[{"selected":[],"title":{"show":true,"text":"","subtext":"","rotate":-90,"textStyle":{"color":"#000000","fontSize":12,"fontFamily":""},"subtextStyle":{"color":"#000000","fontSize":12,"fontFamily":""},"left":"8px","top":"50%"},"axisTick":{"show":true},"axisLine":{"onZero":false},"scale":true,"axisLabel":{"show":true,"rotate":0,"textStyle":{"color":"#000000","fontSize":12,"fontFamily":""},"interval":"auto"},"splitLine":{"show":false,"lineStyle":{"color":"#cccccc","width":1,"type":"solid"}},"zlevel":1}],"colorBy":[{"selected":[]}],"legend":{"show":true,"orientation":"horizontal","left":"50%","right":"auto","top":"10px","bottom":"auto","textStyle":{"color":"#000000","fontSize":12,"fontFamily":"","fontStyle":"normal","fontWeight":"normal","fontDecoration":"none"},"legendMap":[{}],"grid":{"use":false,"rowColumnCount":1}},"noDataMessage":"","plotOptions":{"table":{"formatter":[],"colWidths":[],"rowIndex":{"show":true}},"map":{"geoData":{}}},"source":{"dataType":"lazy","lazyData":[]},"guide":{"message":"Set data options using Chart Setting Button."}},"dataSource":{"selectable":true},"style":{},"group":"7kthr6jiexy662ryt85auudj"}],"layout":{"type":"panel","id":"default-1734127884850"}}],"full":[{"panel":[],"layout":{}}]}}},"meta":{"table":{"type":"table"}},"label":{"en":"Load","ko":"데이터 불러오기"},"context":"python","version":"3.6","func_origin":"brightics.function.io$load13889","outputs":{"table":"t4e82tx2gvfdtvq2"},"fid":"f8hqvvr4rnwyueup"},{"persist-mode":"auto","func":"brightics.function.transform$distinct83807","name":"brightics.function.transform$distinct","param":{"input_cols":["cust_id","ctg_2"]},"display":{"label":"Distinct","diagram":{"position":{"x":520,"y":20}},"sheet":{"in":{"partial":[{"panel":[{"id":"default-1734128795441","chartOption":{"colorSet":["#FD026C","#4682B8","#A5D22D","#F5CC0A","#FE8C01","#6B9494","#B97C46","#84ACD0","#C2E173","#F9DD5B","#FE569D","#FEB356","#9CB8B8","#D0A884","#2E6072","#6D8C1E","#A48806","#A90148","#A95E01","#476363","#7B532F"],"title":{"show":true,"text":"","subtext":"","rotate":0,"textStyle":{"color":"#000000","fontSize":12,"fontFamily":""},"subtextStyle":{"color":"#000000","fontSize":12,"fontFamily":""},"left":"50%","top":"0px"},"toolbar":{"show":false,"right":"8px","top":"8px","orientation":"horizontal","menu":{}},"chart":{"border":"1px #000000 none","background":"rgba(255, 255, 255,1)","animationDuration":1000,"type":"table"},"tooltip":{"triggerOn":"mousemove"},"grid":{"left":"10%","right":"10%","top":"60px","bottom":"60px","width":"auto","height":"auto"},"xAxis":[{"selected":[],"title":{"show":true,"text":"","subtext":"","rotate":0,"textStyle":{"color":"#000000","fontSize":12,"fontFamily":""},"subtextStyle":{"color":"#000000","fontSize":12,"fontFamily":""},"left":"50%","bottom":"5px"},"axisTick":{"show":true},"axisLine":{"onZero":false},"scale":true,"axisLabel":{"show":true,"rotate":0,"textStyle":{"color":"#000000","fontSize":12,"fontFamily":""},"interval":"auto"},"splitLine":{"show":false,"lineStyle":{"color":"#cccccc","width":1,"type":"solid"}},"zlevel":1}],"yAxis":[{"selected":[],"title":{"show":true,"text":"","subtext":"","rotate":-90,"textStyle":{"color":"#000000","fontSize":12,"fontFamily":""},"subtextStyle":{"color":"#000000","fontSize":12,"fontFamily":""},"left":"8px","top":"50%"},"axisTick":{"show":true},"axisLine":{"onZero":false},"scale":true,"axisLabel":{"show":true,"rotate":0,"textStyle":{"color":"#000000","fontSize":12,"fontFamily":""},"interval":"auto"},"splitLine":{"show":false,"lineStyle":{"color":"#cccccc","width":1,"type":"solid"}},"zlevel":1}],"colorBy":[{"selected":[]}],"legend":{"show":true,"orientation":"horizontal","left":"50%","right":"auto","top":"10px","bottom":"auto","textStyle":{"color":"#000000","fontSize":12,"fontFamily":"","fontStyle":"normal","fontWeight":"normal","fontDecoration":"none"},"legendMap":[{}],"grid":{"use":false,"rowColumnCount":1}},"noDataMessage":"","plotOptions":{"table":{"formatter":[],"colWidths":[],"rowIndex":{"show":true}},"map":{"geoData":{}}},"source":{"dataType":"lazy","lazyData":[]},"guide":{"message":"Set data options using Chart Setting Button."}},"dataSource":{"selectable":true},"style":{},"group":"8wgazrpmtzmh5injvwryzrjk"}],"layout":{"type":"panel","id":"default-1734128795441"}}],"full":[{"panel":[],"layout":{}}]},"out":{"partial":[{"panel":[{"id":"default-1734128795496","chartOption":{"colorSet":["#FD026C","#4682B8","#A5D22D","#F5CC0A","#FE8C01","#6B9494","#B97C46","#84ACD0","#C2E173","#F9DD5B","#FE569D","#FEB356","#9CB8B8","#D0A884","#2E6072","#6D8C1E","#A48806","#A90148","#A95E01","#476363","#7B532F"],"title":{"show":true,"text":"","subtext":"","rotate":0,"textStyle":{"color":"#000000","fontSize":12,"fontFamily":""},"subtextStyle":{"color":"#000000","fontSize":12,"fontFamily":""},"left":"50%","top":"0px"},"toolbar":{"show":false,"right":"8px","top":"8px","orientation":"horizontal","menu":{}},"chart":{"border":"1px #000000 none","background":"rgba(255, 255, 255,1)","animationDuration":1000,"type":"table"},"tooltip":{"triggerOn":"mousemove"},"grid":{"left":"10%","right":"10%","top":"60px","bottom":"60px","width":"auto","height":"auto"},"xAxis":[{"selected":[],"title":{"show":true,"text":"","subtext":"","rotate":0,"textStyle":{"color":"#000000","fontSize":12,"fontFamily":""},"subtextStyle":{"color":"#000000","fontSize":12,"fontFamily":""},"left":"50%","bottom":"5px"},"axisTick":{"show":true},"axisLine":{"onZero":false},"scale":true,"axisLabel":{"show":true,"rotate":0,"textStyle":{"color":"#000000","fontSize":12,"fontFamily":""},"interval":"auto"},"splitLine":{"show":false,"lineStyle":{"color":"#cccccc","width":1,"type":"solid"}},"zlevel":1}],"yAxis":[{"selected":[],"title":{"show":true,"text":"","subtext":"","rotate":-90,"textStyle":{"color":"#000000","fontSize":12,"fontFamily":""},"subtextStyle":{"color":"#000000","fontSize":12,"fontFamily":""},"left":"8px","top":"50%"},"axisTick":{"show":true},"axisLine":{"onZero":false},"scale":true,"axisLabel":{"show":true,"rotate":0,"textStyle":{"color":"#000000","fontSize":12,"fontFamily":""},"interval":"auto"},"splitLine":{"show":false,"lineStyle":{"color":"#cccccc","width":1,"type":"solid"}},"zlevel":1}],"colorBy":[{"selected":[]}],"legend":{"show":true,"orientation":"horizontal","left":"50%","right":"auto","top":"10px","bottom":"auto","textStyle":{"color":"#000000","fontSize":12,"fontFamily":"","fontStyle":"normal","fontWeight":"normal","fontDecoration":"none"},"legendMap":[{}],"grid":{"use":false,"rowColumnCount":1}},"noDataMessage":"","plotOptions":{"table":{"formatter":[],"colWidths":[],"rowIndex":{"show":true}},"map":{"geoData":{}}},"source":{"dataType":"lazy","lazyData":[]},"guide":{"message":"Set data options using Chart Setting Button."}},"dataSource":{"selectable":true},"style":{},"group":"ypzx5y4fwmfik5vk4cfcirtk"}],"layout":{"type":"panel","id":"default-1734128795496"}}],"full":[{"panel":[],"layout":{}}]}}},"meta":{"table":{"type":"table","desc":" Data in a table","optional":false},"out_table":{"type":"table","desc":"A table with duplicate removed"}},"label":{"en":"Distinct","ko":"중복행 제거"},"context":"python","version":"3.6","func_origin":"brightics.function.transform$distinct83807","inputs":{"table":"t4e82tx2gvfdtvq2"},"outputs":{"out_table":"tue3t8ytgj4pfjzs"},"fid":"fbzfmc4z9wn6g8en"},{"persist-mode":"auto","func":"brightics.function.statistics$statistic_summary80870","name":"brightics.function.statistics$statistic_summary","param":{"statistics":["nrow"],"input_cols":["cust_id"],"group_by":["cust_id"]},"display":{"label":"Statistic Summary","diagram":{"position":{"x":770,"y":120}},"sheet":{"in":{"partial":[{"panel":[{"id":"default-1734128855110","chartOption":{"colorSet":["#FD026C","#4682B8","#A5D22D","#F5CC0A","#FE8C01","#6B9494","#B97C46","#84ACD0","#C2E173","#F9DD5B","#FE569D","#FEB356","#9CB8B8","#D0A884","#2E6072","#6D8C1E","#A48806","#A90148","#A95E01","#476363","#7B532F"],"title":{"show":true,"text":"","subtext":"","rotate":0,"textStyle":{"color":"#000000","fontSize":12,"fontFamily":""},"subtextStyle":{"color":"#000000","fontSize":12,"fontFamily":""},"left":"50%","top":"0px"},"toolbar":{"show":false,"right":"8px","top":"8px","orientation":"horizontal","menu":{}},"chart":{"border":"1px #000000 none","background":"rgba(255, 255, 255,1)","animationDuration":1000,"type":"table"},"tooltip":{"triggerOn":"mousemove"},"grid":{"left":"10%","right":"10%","top":"60px","bottom":"60px","width":"auto","height":"auto"},"xAxis":[{"selected":[],"title":{"show":true,"text":"","subtext":"","rotate":0,"textStyle":{"color":"#000000","fontSize":12,"fontFamily":""},"subtextStyle":{"color":"#000000","fontSize":12,"fontFamily":""},"left":"50%","bottom":"5px"},"axisTick":{"show":true},"axisLine":{"onZero":false},"scale":true,"axisLabel":{"show":true,"rotate":0,"textStyle":{"color":"#000000","fontSize":12,"fontFamily":""},"interval":"auto"},"splitLine":{"show":false,"lineStyle":{"color":"#cccccc","width":1,"type":"solid"}},"zlevel":1}],"yAxis":[{"selected":[],"title":{"show":true,"text":"","subtext":"","rotate":-90,"textStyle":{"color":"#000000","fontSize":12,"fontFamily":""},"subtextStyle":{"color":"#000000","fontSize":12,"fontFamily":""},"left":"8px","top":"50%"},"axisTick":{"show":true},"axisLine":{"onZero":false},"scale":true,"axisLabel":{"show":true,"rotate":0,"textStyle":{"color":"#000000","fontSize":12,"fontFamily":""},"interval":"auto"},"splitLine":{"show":false,"lineStyle":{"color":"#cccccc","width":1,"type":"solid"}},"zlevel":1}],"colorBy":[{"selected":[]}],"legend":{"show":true,"orientation":"horizontal","left":"50%","right":"auto","top":"10px","bottom":"auto","textStyle":{"color":"#000000","fontSize":12,"fontFamily":"","fontStyle":"normal","fontWeight":"normal","fontDecoration":"none"},"legendMap":[{}],"grid":{"use":false,"rowColumnCount":1}},"noDataMessage":"","plotOptions":{"table":{"formatter":[],"colWidths":[],"rowIndex":{"show":true}},"map":{"geoData":{}}},"source":{"dataType":"lazy","lazyData":[]},"guide":{"message":"Set data options using Chart Setting Button."}},"dataSource":{"selectable":true},"style":{},"group":"wefc4ruhxxay3i59s6izj9uc"}],"layout":{"type":"panel","id":"default-1734128855110"}}],"full":[{"panel":[],"layout":{}}]},"out":{"partial":[{"panel":[{"id":"default-1734128855189","chartOption":{"colorSet":["#FD026C","#4682B8","#A5D22D","#F5CC0A","#FE8C01","#6B9494","#B97C46","#84ACD0","#C2E173","#F9DD5B","#FE569D","#FEB356","#9CB8B8","#D0A884","#2E6072","#6D8C1E","#A48806","#A90148","#A95E01","#476363","#7B532F"],"title":{"show":true,"text":"","subtext":"","rotate":0,"textStyle":{"color":"#000000","fontSize":12,"fontFamily":""},"subtextStyle":{"color":"#000000","fontSize":12,"fontFamily":""},"left":"50%","top":"0px"},"toolbar":{"show":false,"right":"8px","top":"8px","orientation":"horizontal","menu":{}},"chart":{"border":"1px #000000 none","background":"rgba(255, 255, 255,1)","animationDuration":1000,"type":"table"},"tooltip":{"triggerOn":"mousemove"},"grid":{"left":"10%","right":"10%","top":"60px","bottom":"60px","width":"auto","height":"auto"},"xAxis":[{"selected":[],"title":{"show":true,"text":"","subtext":"","rotate":0,"textStyle":{"color":"#000000","fontSize":12,"fontFamily":""},"subtextStyle":{"color":"#000000","fontSize":12,"fontFamily":""},"left":"50%","bottom":"5px"},"axisTick":{"show":true},"axisLine":{"onZero":false},"scale":true,"axisLabel":{"show":true,"rotate":0,"textStyle":{"color":"#000000","fontSize":12,"fontFamily":""},"interval":"auto"},"splitLine":{"show":false,"lineStyle":{"color":"#cccccc","width":1,"type":"solid"}},"zlevel":1}],"yAxis":[{"selected":[],"title":{"show":true,"text":"","subtext":"","rotate":-90,"textStyle":{"color":"#000000","fontSize":12,"fontFamily":""},"subtextStyle":{"color":"#000000","fontSize":12,"fontFamily":""},"left":"8px","top":"50%"},"axisTick":{"show":true},"axisLine":{"onZero":false},"scale":true,"axisLabel":{"show":true,"rotate":0,"textStyle":{"color":"#000000","fontSize":12,"fontFamily":""},"interval":"auto"},"splitLine":{"show":false,"lineStyle":{"color":"#cccccc","width":1,"type":"solid"}},"zlevel":1}],"colorBy":[{"selected":[]}],"legend":{"show":true,"orientation":"horizontal","left":"50%","right":"auto","top":"10px","bottom":"auto","textStyle":{"color":"#000000","fontSize":12,"fontFamily":"","fontStyle":"normal","fontWeight":"normal","fontDecoration":"none"},"legendMap":[{}],"grid":{"use":false,"rowColumnCount":1}},"noDataMessage":"","plotOptions":{"table":{"formatter":[],"colWidths":[],"rowIndex":{"show":true}},"map":{"geoData":{}}},"source":{"dataType":"lazy","lazyData":[]},"guide":{"message":"Set data options using Chart Setting Button."}},"dataSource":{"selectable":true},"style":{},"group":"zet3anvm8ywj935cvdj2ans3"}],"layout":{"type":"panel","id":"default-1734128855189"}}],"full":[{"panel":[],"layout":{}}]}}},"meta":{"table":{"type":"table"},"out_table":{"type":"table"}},"label":{"en":"Statistic Summary","ko":"통계 요약"},"context":"python","version":"3.6","func_origin":"brightics.function.statistics$statistic_summary80870","inputs":{"table":"tue3t8ytgj4pfjzs"},"outputs":{"out_table":"tr34enm54vzx6je4"},"fid":"fmare7xmyva3qv7r"},{"persist-mode":"auto","func":"simpleFilterPython","name":"brightics.function.manipulation$simple_filter","label":"Filter","context":"python","version":"3.6","param":{"main_operator":"and","input_cols":["nrow"],"operators":[">"],"operands":["1"]},"inputs":{"table":"tr34enm54vzx6je4"},"outputs":{"out_table":"t48byqjtrq6qnwkq"},"meta":{"table":{"type":"table"},"out_table":{"type":"table"}},"display":{"label":"Filter","diagram":{"position":{"x":1020,"y":120}},"sheet":{"in":{"partial":[{"panel":[{"id":"default-1734128911550","chartOption":{"colorSet":["#FD026C","#4682B8","#A5D22D","#F5CC0A","#FE8C01","#6B9494","#B97C46","#84ACD0","#C2E173","#F9DD5B","#FE569D","#FEB356","#9CB8B8","#D0A884","#2E6072","#6D8C1E","#A48806","#A90148","#A95E01","#476363","#7B532F"],"title":{"show":true,"text":"","subtext":"","rotate":0,"textStyle":{"color":"#000000","fontSize":12,"fontFamily":""},"subtextStyle":{"color":"#000000","fontSize":12,"fontFamily":""},"left":"50%","top":"0px"},"toolbar":{"show":false,"right":"8px","top":"8px","orientation":"horizontal","menu":{}},"chart":{"border":"1px #000000 none","background":"rgba(255, 255, 255,1)","animationDuration":1000,"type":"table"},"tooltip":{"triggerOn":"mousemove"},"grid":{"left":"10%","right":"10%","top":"60px","bottom":"60px","width":"auto","height":"auto"},"xAxis":[{"selected":[],"title":{"show":true,"text":"","subtext":"","rotate":0,"textStyle":{"color":"#000000","fontSize":12,"fontFamily":""},"subtextStyle":{"color":"#000000","fontSize":12,"fontFamily":""},"left":"50%","bottom":"5px"},"axisTick":{"show":true},"axisLine":{"onZero":false},"scale":true,"axisLabel":{"show":true,"rotate":0,"textStyle":{"color":"#000000","fontSize":12,"fontFamily":""},"interval":"auto"},"splitLine":{"show":false,"lineStyle":{"color":"#cccccc","width":1,"type":"solid"}},"zlevel":1}],"yAxis":[{"selected":[],"title":{"show":true,"text":"","subtext":"","rotate":-90,"textStyle":{"color":"#000000","fontSize":12,"fontFamily":""},"subtextStyle":{"color":"#000000","fontSize":12,"fontFamily":""},"left":"8px","top":"50%"},"axisTick":{"show":true},"axisLine":{"onZero":false},"scale":true,"axisLabel":{"show":true,"rotate":0,"textStyle":{"color":"#000000","fontSize":12,"fontFamily":""},"interval":"auto"},"splitLine":{"show":false,"lineStyle":{"color":"#cccccc","width":1,"type":"solid"}},"zlevel":1}],"colorBy":[{"selected":[]}],"legend":{"show":true,"orientation":"horizontal","left":"50%","right":"auto","top":"10px","bottom":"auto","textStyle":{"color":"#000000","fontSize":12,"fontFamily":"","fontStyle":"normal","fontWeight":"normal","fontDecoration":"none"},"legendMap":[{}],"grid":{"use":false,"rowColumnCount":1}},"noDataMessage":"","plotOptions":{"table":{"formatter":[],"colWidths":[],"rowIndex":{"show":true}},"map":{"geoData":{}}},"source":{"dataType":"lazy","lazyData":[]},"guide":{"message":"Set data options using Chart Setting Button."}},"dataSource":{"selectable":true},"style":{},"group":"p5g5irbnef9w8yswq97anzbr"}],"layout":{"type":"panel","id":"default-1734128911550"}}],"full":[{"panel":[],"layout":{}}]},"out":{"partial":[{"panel":[{"id":"default-1734128911608","chartOption":{"colorSet":["#FD026C","#4682B8","#A5D22D","#F5CC0A","#FE8C01","#6B9494","#B97C46","#84ACD0","#C2E173","#F9DD5B","#FE569D","#FEB356","#9CB8B8","#D0A884","#2E6072","#6D8C1E","#A48806","#A90148","#A95E01","#476363","#7B532F"],"title":{"show":true,"text":"","subtext":"","rotate":0,"textStyle":{"color":"#000000","fontSize":12,"fontFamily":""},"subtextStyle":{"color":"#000000","fontSize":12,"fontFamily":""},"left":"50%","top":"0px"},"toolbar":{"show":false,"right":"8px","top":"8px","orientation":"horizontal","menu":{}},"chart":{"border":"1px #000000 none","background":"rgba(255, 255, 255,1)","animationDuration":1000,"type":"table"},"tooltip":{"triggerOn":"mousemove"},"grid":{"left":"10%","right":"10%","top":"60px","bottom":"60px","width":"auto","height":"auto"},"xAxis":[{"selected":[],"title":{"show":true,"text":"","subtext":"","rotate":0,"textStyle":{"color":"#000000","fontSize":12,"fontFamily":""},"subtextStyle":{"color":"#000000","fontSize":12,"fontFamily":""},"left":"50%","bottom":"5px"},"axisTick":{"show":true},"axisLine":{"onZero":false},"scale":true,"axisLabel":{"show":true,"rotate":0,"textStyle":{"color":"#000000","fontSize":12,"fontFamily":""},"interval":"auto"},"splitLine":{"show":false,"lineStyle":{"color":"#cccccc","width":1,"type":"solid"}},"zlevel":1}],"yAxis":[{"selected":[],"title":{"show":true,"text":"","subtext":"","rotate":-90,"textStyle":{"color":"#000000","fontSize":12,"fontFamily":""},"subtextStyle":{"color":"#000000","fontSize":12,"fontFamily":""},"left":"8px","top":"50%"},"axisTick":{"show":true},"axisLine":{"onZero":false},"scale":true,"axisLabel":{"show":true,"rotate":0,"textStyle":{"color":"#000000","fontSize":12,"fontFamily":""},"interval":"auto"},"splitLine":{"show":false,"lineStyle":{"color":"#cccccc","width":1,"type":"solid"}},"zlevel":1}],"colorBy":[{"selected":[]}],"legend":{"show":true,"orientation":"horizontal","left":"50%","right":"auto","top":"10px","bottom":"auto","textStyle":{"color":"#000000","fontSize":12,"fontFamily":"","fontStyle":"normal","fontWeight":"normal","fontDecoration":"none"},"legendMap":[{}],"grid":{"use":false,"rowColumnCount":1}},"noDataMessage":"","plotOptions":{"table":{"formatter":[],"colWidths":[],"rowIndex":{"show":true}},"map":{"geoData":{}}},"source":{"dataType":"lazy","lazyData":[]},"guide":{"message":"Set data options using Chart Setting Button."}},"dataSource":{"selectable":true},"style":{},"group":"qycyag5zqxid8pm4us2vhs2s"}],"layout":{"type":"panel","id":"default-1734128911608"}}],"full":[{"panel":[],"layout":{}}]}}},"fid":"fexfpe2zupg288nb"},{"persist-mode":"auto","context":"python","func":"merge","name":"brightics.function.transform$join","label":"Join","version":"3.6","inputs":{"left_table":"t48byqjtrq6qnwkq","right_table":"tue3t8ytgj4pfjzs"},"outputs":{"table":"tg4k2vgavyw693mq"},"meta":{"left_table":{"type":"table"},"right_table":{"type":"table"},"table":{"type":"table"}},"param":{"left_on":["cust_id"],"right_on":["cust_id"],"how":"inner","lsuffix":"","rsuffix":"","sort":"false"},"display":{"label":"Join","diagram":{"position":{"x":1270,"y":20}},"sheet":{"in":{"partial":[{"panel":[{"id":"default-1734129000462","chartOption":{"colorSet":["#FD026C","#4682B8","#A5D22D","#F5CC0A","#FE8C01","#6B9494","#B97C46","#84ACD0","#C2E173","#F9DD5B","#FE569D","#FEB356","#9CB8B8","#D0A884","#2E6072","#6D8C1E","#A48806","#A90148","#A95E01","#476363","#7B532F"],"title":{"show":true,"text":"","subtext":"","rotate":0,"textStyle":{"color":"#000000","fontSize":12,"fontFamily":""},"subtextStyle":{"color":"#000000","fontSize":12,"fontFamily":""},"left":"50%","top":"0px"},"toolbar":{"show":false,"right":"8px","top":"8px","orientation":"horizontal","menu":{}},"chart":{"border":"1px #000000 none","background":"rgba(255, 255, 255,1)","animationDuration":1000,"type":"table"},"tooltip":{"triggerOn":"mousemove"},"grid":{"left":"10%","right":"10%","top":"60px","bottom":"60px","width":"auto","height":"auto"},"xAxis":[{"selected":[],"title":{"show":true,"text":"","subtext":"","rotate":0,"textStyle":{"color":"#000000","fontSize":12,"fontFamily":""},"subtextStyle":{"color":"#000000","fontSize":12,"fontFamily":""},"left":"50%","bottom":"5px"},"axisTick":{"show":true},"axisLine":{"onZero":false},"scale":true,"axisLabel":{"show":true,"rotate":0,"textStyle":{"color":"#000000","fontSize":12,"fontFamily":""},"interval":"auto"},"splitLine":{"show":false,"lineStyle":{"color":"#cccccc","width":1,"type":"solid"}},"zlevel":1}],"yAxis":[{"selected":[],"title":{"show":true,"text":"","subtext":"","rotate":-90,"textStyle":{"color":"#000000","fontSize":12,"fontFamily":""},"subtextStyle":{"color":"#000000","fontSize":12,"fontFamily":""},"left":"8px","top":"50%"},"axisTick":{"show":true},"axisLine":{"onZero":false},"scale":true,"axisLabel":{"show":true,"rotate":0,"textStyle":{"color":"#000000","fontSize":12,"fontFamily":""},"interval":"auto"},"splitLine":{"show":false,"lineStyle":{"color":"#cccccc","width":1,"type":"solid"}},"zlevel":1}],"colorBy":[{"selected":[]}],"legend":{"show":true,"orientation":"horizontal","left":"50%","right":"auto","top":"10px","bottom":"auto","textStyle":{"color":"#000000","fontSize":12,"fontFamily":"","fontStyle":"normal","fontWeight":"normal","fontDecoration":"none"},"legendMap":[{}],"grid":{"use":false,"rowColumnCount":1}},"noDataMessage":"","plotOptions":{"table":{"formatter":[],"colWidths":[],"rowIndex":{"show":true}},"map":{"geoData":{}}},"source":{"dataType":"lazy","lazyData":[]},"guide":{"message":"Set data options using Chart Setting Button."}},"dataSource":{"selectable":true},"style":{},"group":"rcwixng25zr2bvj8jzvxsrmr"}],"layout":{"type":"panel","id":"default-1734129000462"}}],"full":[{"panel":[],"layout":{}}]},"out":{"partial":[{"panel":[{"id":"default-1734129000525","chartOption":{"colorSet":["#FD026C","#4682B8","#A5D22D","#F5CC0A","#FE8C01","#6B9494","#B97C46","#84ACD0","#C2E173","#F9DD5B","#FE569D","#FEB356","#9CB8B8","#D0A884","#2E6072","#6D8C1E","#A48806","#A90148","#A95E01","#476363","#7B532F"],"title":{"show":true,"text":"","subtext":"","rotate":0,"textStyle":{"color":"#000000","fontSize":12,"fontFamily":""},"subtextStyle":{"color":"#000000","fontSize":12,"fontFamily":""},"left":"50%","top":"0px"},"toolbar":{"show":false,"right":"8px","top":"8px","orientation":"horizontal","menu":{}},"chart":{"border":"1px #000000 none","background":"rgba(255, 255, 255,1)","animationDuration":1000,"type":"table"},"tooltip":{"triggerOn":"mousemove"},"grid":{"left":"10%","right":"10%","top":"60px","bottom":"60px","width":"auto","height":"auto"},"xAxis":[{"selected":[],"title":{"show":true,"text":"","subtext":"","rotate":0,"textStyle":{"color":"#000000","fontSize":12,"fontFamily":""},"subtextStyle":{"color":"#000000","fontSize":12,"fontFamily":""},"left":"50%","bottom":"5px"},"axisTick":{"show":true},"axisLine":{"onZero":false},"scale":true,"axisLabel":{"show":true,"rotate":0,"textStyle":{"color":"#000000","fontSize":12,"fontFamily":""},"interval":"auto"},"splitLine":{"show":false,"lineStyle":{"color":"#cccccc","width":1,"type":"solid"}},"zlevel":1}],"yAxis":[{"selected":[],"title":{"show":true,"text":"","subtext":"","rotate":-90,"textStyle":{"color":"#000000","fontSize":12,"fontFamily":""},"subtextStyle":{"color":"#000000","fontSize":12,"fontFamily":""},"left":"8px","top":"50%"},"axisTick":{"show":true},"axisLine":{"onZero":false},"scale":true,"axisLabel":{"show":true,"rotate":0,"textStyle":{"color":"#000000","fontSize":12,"fontFamily":""},"interval":"auto"},"splitLine":{"show":false,"lineStyle":{"color":"#cccccc","width":1,"type":"solid"}},"zlevel":1}],"colorBy":[{"selected":[]}],"legend":{"show":true,"orientation":"horizontal","left":"50%","right":"auto","top":"10px","bottom":"auto","textStyle":{"color":"#000000","fontSize":12,"fontFamily":"","fontStyle":"normal","fontWeight":"normal","fontDecoration":"none"},"legendMap":[{}],"grid":{"use":false,"rowColumnCount":1}},"noDataMessage":"","plotOptions":{"table":{"formatter":[],"colWidths":[],"rowIndex":{"show":true}},"map":{"geoData":{}}},"source":{"dataType":"lazy","lazyData":[]},"guide":{"message":"Set data options using Chart Setting Button."}},"dataSource":{"selectable":true},"style":{},"group":"g89n6af23zz48j94wt73y5jk"}],"layout":{"type":"panel","id":"default-1734129000525"}}],"full":[{"panel":[],"layout":{}}]}}},"fid":"fzkrcuh3zzedhpk9"},{"persist-mode":"auto","func":"brightics.function.recommendation$association_rule03961","name":"brightics.function.recommendation$association_rule","param":{"input_mode":"item_user","user_name":"cust_id","items":"ctg_2","min_support":0.01,"min_confidence":0.01},"display":{"label":"Association Rule","diagram":{"position":{"x":1520,"y":20}},"sheet":{"in":{"partial":[{"panel":[{"id":"default-1734129051739","chartOption":{"colorSet":["#FD026C","#4682B8","#A5D22D","#F5CC0A","#FE8C01","#6B9494","#B97C46","#84ACD0","#C2E173","#F9DD5B","#FE569D","#FEB356","#9CB8B8","#D0A884","#2E6072","#6D8C1E","#A48806","#A90148","#A95E01","#476363","#7B532F"],"title":{"show":true,"text":"","subtext":"","rotate":0,"textStyle":{"color":"#000000","fontSize":12,"fontFamily":""},"subtextStyle":{"color":"#000000","fontSize":12,"fontFamily":""},"left":"50%","top":"0px"},"toolbar":{"show":false,"right":"8px","top":"8px","orientation":"horizontal","menu":{}},"chart":{"border":"1px #000000 none","background":"rgba(255, 255, 255,1)","animationDuration":1000,"type":"table"},"tooltip":{"triggerOn":"mousemove"},"grid":{"left":"10%","right":"10%","top":"60px","bottom":"60px","width":"auto","height":"auto"},"xAxis":[{"selected":[],"title":{"show":true,"text":"","subtext":"","rotate":0,"textStyle":{"color":"#000000","fontSize":12,"fontFamily":""},"subtextStyle":{"color":"#000000","fontSize":12,"fontFamily":""},"left":"50%","bottom":"5px"},"axisTick":{"show":true},"axisLine":{"onZero":false},"scale":true,"axisLabel":{"show":true,"rotate":0,"textStyle":{"color":"#000000","fontSize":12,"fontFamily":""},"interval":"auto"},"splitLine":{"show":false,"lineStyle":{"color":"#cccccc","width":1,"type":"solid"}},"zlevel":1}],"yAxis":[{"selected":[],"title":{"show":true,"text":"","subtext":"","rotate":-90,"textStyle":{"color":"#000000","fontSize":12,"fontFamily":""},"subtextStyle":{"color":"#000000","fontSize":12,"fontFamily":""},"left":"8px","top":"50%"},"axisTick":{"show":true},"axisLine":{"onZero":false},"scale":true,"axisLabel":{"show":true,"rotate":0,"textStyle":{"color":"#000000","fontSize":12,"fontFamily":""},"interval":"auto"},"splitLine":{"show":false,"lineStyle":{"color":"#cccccc","width":1,"type":"solid"}},"zlevel":1}],"colorBy":[{"selected":[]}],"legend":{"show":true,"orientation":"horizontal","left":"50%","right":"auto","top":"10px","bottom":"auto","textStyle":{"color":"#000000","fontSize":12,"fontFamily":"","fontStyle":"normal","fontWeight":"normal","fontDecoration":"none"},"legendMap":[{}],"grid":{"use":false,"rowColumnCount":1}},"noDataMessage":"","plotOptions":{"table":{"formatter":[],"colWidths":[],"rowIndex":{"show":true}},"map":{"geoData":{}}},"source":{"dataType":"lazy","lazyData":[]},"guide":{"message":"Set data options using Chart Setting Button."}},"dataSource":{"selectable":true},"style":{},"group":"5yjgkuuciehuvmf7qf9nuuh9"}],"layout":{"type":"panel","id":"default-1734129051739"}}],"full":[{"panel":[],"layout":{}}]},"out":{"partial":[{"panel":[{"id":"default-1734129051804","chartOption":{"colorSet":["#FD026C","#4682B8","#A5D22D","#F5CC0A","#FE8C01","#6B9494","#B97C46","#84ACD0","#C2E173","#F9DD5B","#FE569D","#FEB356","#9CB8B8","#D0A884","#2E6072","#6D8C1E","#A48806","#A90148","#A95E01","#476363","#7B532F"],"title":{"show":true,"text":"","subtext":"","rotate":0,"textStyle":{"color":"#000000","fontSize":12,"fontFamily":""},"subtextStyle":{"color":"#000000","fontSize":12,"fontFamily":""},"left":"50%","top":"0px"},"toolbar":{"show":false,"right":"8px","top":"8px","orientation":"horizontal","menu":{}},"chart":{"border":"1px #000000 none","background":"rgba(255, 255, 255,1)","animationDuration":1000,"type":"table"},"tooltip":{"triggerOn":"mousemove"},"grid":{"left":"10%","right":"10%","top":"60px","bottom":"60px","width":"auto","height":"auto"},"xAxis":[{"selected":[],"title":{"show":true,"text":"","subtext":"","rotate":0,"textStyle":{"color":"#000000","fontSize":12,"fontFamily":""},"subtextStyle":{"color":"#000000","fontSize":12,"fontFamily":""},"left":"50%","bottom":"5px"},"axisTick":{"show":true},"axisLine":{"onZero":false},"scale":true,"axisLabel":{"show":true,"rotate":0,"textStyle":{"color":"#000000","fontSize":12,"fontFamily":""},"interval":"auto"},"splitLine":{"show":false,"lineStyle":{"color":"#cccccc","width":1,"type":"solid"}},"zlevel":1}],"yAxis":[{"selected":[],"title":{"show":true,"text":"","subtext":"","rotate":-90,"textStyle":{"color":"#000000","fontSize":12,"fontFamily":""},"subtextStyle":{"color":"#000000","fontSize":12,"fontFamily":""},"left":"8px","top":"50%"},"axisTick":{"show":true},"axisLine":{"onZero":false},"scale":true,"axisLabel":{"show":true,"rotate":0,"textStyle":{"color":"#000000","fontSize":12,"fontFamily":""},"interval":"auto"},"splitLine":{"show":false,"lineStyle":{"color":"#cccccc","width":1,"type":"solid"}},"zlevel":1}],"colorBy":[{"selected":[]}],"legend":{"show":true,"orientation":"horizontal","left":"50%","right":"auto","top":"10px","bottom":"auto","textStyle":{"color":"#000000","fontSize":12,"fontFamily":"","fontStyle":"normal","fontWeight":"normal","fontDecoration":"none"},"legendMap":[{}],"grid":{"use":false,"rowColumnCount":1}},"noDataMessage":"","plotOptions":{"table":{"formatter":[],"colWidths":[],"rowIndex":{"show":true}},"map":{"geoData":{}}},"source":{"dataType":"lazy","lazyData":[]},"guide":{"message":"Set data options using Chart Setting Button."}},"dataSource":{"selectable":true},"style":{},"group":"fn66r8zgpicie7v63hespeis"}],"layout":{"type":"panel","id":"default-1734129051804"}}],"full":[{"panel":[],"layout":{}}]}}},"meta":{"table":{"type":"table"},"out_table":{"type":"table"}},"label":{"en":"Association Rule","ko":"연관 규칙"},"context":"python","version":"3.6","func_origin":"brightics.function.recommendation$association_rule03961","inputs":{"table":"tg4k2vgavyw693mq"},"outputs":{"out_table":"ttuqsrbysr368t24"},"fid":"fwcmrnpbzehvs4s3"},{"persist-mode":"auto","func":"queryExecutorPython","name":"brightics.function.transform$sql_execute","label":"Query Executor","context":"python","version":"3.6","param":{"query":"SELECT  \nitem_1\n, item_2\n, support, confidence, lift, conviction\nFROM (\n  SELECT\n  concat_ws(',',antecedent) as item_1\n  , concat_ws(',',consequent) as item_2\n  , support, confidence, lift, conviction\n  FROM  #{DF(0)}\n  WHERE lift > 1\n  order by support desc\n  )\nWHERE length(item_1) - length(regexp_replace(item_1, \",\", \"\")) + 1  == 1"},"inputs":{"tables":["ttuqsrbysr368t24"]},"outputs":{"out_table":"tmdzrn5jpqt3msj9"},"meta":{"tables":{"type":"table","range":{"min":1,"max":10}},"out_table":{"type":"table"}},"display":{"label":"Query Executor","diagram":{"position":{"x":1770,"y":20}},"sheet":{"in":{"partial":[{"panel":[{"id":"default-1734129256916","chartOption":{"colorSet":["#FD026C","#4682B8","#A5D22D","#F5CC0A","#FE8C01","#6B9494","#B97C46","#84ACD0","#C2E173","#F9DD5B","#FE569D","#FEB356","#9CB8B8","#D0A884","#2E6072","#6D8C1E","#A48806","#A90148","#A95E01","#476363","#7B532F"],"title":{"show":true,"text":"","subtext":"","rotate":0,"textStyle":{"color":"#000000","fontSize":12,"fontFamily":""},"subtextStyle":{"color":"#000000","fontSize":12,"fontFamily":""},"left":"50%","top":"0px"},"toolbar":{"show":false,"right":"8px","top":"8px","orientation":"horizontal","menu":{}},"chart":{"border":"1px #000000 none","background":"rgba(255, 255, 255,1)","animationDuration":1000,"type":"table"},"tooltip":{"triggerOn":"mousemove"},"grid":{"left":"10%","right":"10%","top":"60px","bottom":"60px","width":"auto","height":"auto"},"xAxis":[{"selected":[],"title":{"show":true,"text":"","subtext":"","rotate":0,"textStyle":{"color":"#000000","fontSize":12,"fontFamily":""},"subtextStyle":{"color":"#000000","fontSize":12,"fontFamily":""},"left":"50%","bottom":"5px"},"axisTick":{"show":true},"axisLine":{"onZero":false},"scale":true,"axisLabel":{"show":true,"rotate":0,"textStyle":{"color":"#000000","fontSize":12,"fontFamily":""},"interval":"auto"},"splitLine":{"show":false,"lineStyle":{"color":"#cccccc","width":1,"type":"solid"}},"zlevel":1}],"yAxis":[{"selected":[],"title":{"show":true,"text":"","subtext":"","rotate":-90,"textStyle":{"color":"#000000","fontSize":12,"fontFamily":""},"subtextStyle":{"color":"#000000","fontSize":12,"fontFamily":""},"left":"8px","top":"50%"},"axisTick":{"show":true},"axisLine":{"onZero":false},"scale":true,"axisLabel":{"show":true,"rotate":0,"textStyle":{"color":"#000000","fontSize":12,"fontFamily":""},"interval":"auto"},"splitLine":{"show":false,"lineStyle":{"color":"#cccccc","width":1,"type":"solid"}},"zlevel":1}],"colorBy":[{"selected":[]}],"legend":{"show":true,"orientation":"horizontal","left":"50%","right":"auto","top":"10px","bottom":"auto","textStyle":{"color":"#000000","fontSize":12,"fontFamily":"","fontStyle":"normal","fontWeight":"normal","fontDecoration":"none"},"legendMap":[{}],"grid":{"use":false,"rowColumnCount":1}},"noDataMessage":"","plotOptions":{"table":{"formatter":[],"colWidths":[],"rowIndex":{"show":true}},"map":{"geoData":{}}},"source":{"dataType":"lazy","lazyData":[]},"guide":{"message":"Set data options using Chart Setting Button."}},"dataSource":{"selectable":true},"style":{},"group":"7cwfmzh5rhsye92czwbvcwbf"}],"layout":{"type":"panel","id":"default-1734129256916"}}],"full":[{"panel":[],"layout":{}}]},"out":{"partial":[{"panel":[{"id":"default-1734129257006","chartOption":{"colorSet":["#FD026C","#4682B8","#A5D22D","#F5CC0A","#FE8C01","#6B9494","#B97C46","#84ACD0","#C2E173","#F9DD5B","#FE569D","#FEB356","#9CB8B8","#D0A884","#2E6072","#6D8C1E","#A48806","#A90148","#A95E01","#476363","#7B532F"],"title":{"show":true,"text":"","subtext":"","rotate":0,"textStyle":{"color":"#000000","fontSize":12,"fontFamily":""},"subtextStyle":{"color":"#000000","fontSize":12,"fontFamily":""},"left":"50%","top":"0px"},"toolbar":{"show":false,"right":"8px","top":"8px","orientation":"horizontal","menu":{}},"chart":{"border":"1px #000000 none","background":"rgba(255, 255, 255,1)","animationDuration":1000,"type":"network"},"tooltip":{"triggerOn":"mousemove"},"grid":{"left":"10%","right":"10%","top":"60px","bottom":"60px","width":"auto","height":"auto"},"xAxis":[{"selected":[],"title":{"show":true,"text":"","subtext":"","rotate":0,"textStyle":{"color":"#000000","fontSize":12,"fontFamily":""},"subtextStyle":{"color":"#000000","fontSize":12,"fontFamily":""},"left":"50%","bottom":"5px"},"axisTick":{"show":true},"axisLine":{"onZero":false},"scale":true,"axisLabel":{"show":true,"rotate":0,"textStyle":{"color":"#000000","fontSize":12,"fontFamily":""},"interval":"auto"},"splitLine":{"show":false,"lineStyle":{"color":"#cccccc","width":1,"type":"solid"}},"zlevel":1}],"yAxis":[{"selected":[],"title":{"show":true,"text":"","subtext":"","rotate":-90,"textStyle":{"color":"#000000","fontSize":12,"fontFamily":""},"subtextStyle":{"color":"#000000","fontSize":12,"fontFamily":""},"left":"8px","top":"50%"},"axisTick":{"show":true},"axisLine":{"onZero":false},"scale":true,"axisLabel":{"show":true,"rotate":0,"textStyle":{"color":"#000000","fontSize":12,"fontFamily":""},"interval":"auto"},"splitLine":{"show":false,"lineStyle":{"color":"#cccccc","width":1,"type":"solid"}},"zlevel":1}],"colorBy":[{"selected":[]}],"legend":{"show":true,"orientation":"horizontal","left":"50%","right":"auto","top":"10px","bottom":"auto","textStyle":{"color":"#000000","fontSize":12,"fontFamily":"","fontStyle":"normal","fontWeight":"normal","fontDecoration":"none"},"legendMap":[{}],"grid":{"use":false,"rowColumnCount":1}},"noDataMessage":"","plotOptions":{"network":{"fromColumn":[{"selected":[{"value":"item_1","name":"item_1","type":"String"}],"axisType":null}],"toColumn":[{"selected":[{"value":"item_2","name":"item_2","type":"String"}],"axisType":null}],"nodeSizeBy":[{"selected":[{"value":"confidence","name":"confidence","type":"Double","aggregation":"average"}]}],"label":{"normal":{"show":true,"textStyle":{"color":"#000000","fontSize":12,"fontFamily":"","fontStyle":"normal","fontWeight":"normal"}}},"style":{"node":{"size":1,"color":"#4682B8"},"link":{"color":"#FD026C","opacity":1,"width":1},"edge":{"symbol":["none","none"],"size":[10,10]}}},"map":{"geoData":{}}},"source":{"dataType":"lazy","lazyData":[]},"guide":{"message":"Set data options using Chart Setting Button."}},"dataSource":{"selectable":true},"style":{},"group":"h3vdy4bzg6sicfcr27jr4d8h"}],"layout":{"type":"panel","id":"default-1734129257006"}}],"full":[{"panel":[],"layout":{}}]}}},"fid":"fpznmzcz9cn9dq9t"}],"links":[{"kid":"kc8fdnm26gdra89h","sourceFid":"f8hqvvr4rnwyueup","targetFid":"fbzfmc4z9wn6g8en"},{"kid":"kwnagq9hjynn7xhe","sourceFid":"fbzfmc4z9wn6g8en","targetFid":"fmare7xmyva3qv7r"},{"kid":"kbvv4u4tyfbnauvn","sourceFid":"fmare7xmyva3qv7r","targetFid":"fexfpe2zupg288nb"},{"kid":"km4u2ancbvk8quxy","sourceFid":"fexfpe2zupg288nb","targetFid":"fzkrcuh3zzedhpk9"},{"kid":"k2k477fauuwczxpb","sourceFid":"fbzfmc4z9wn6g8en","targetFid":"fzkrcuh3zzedhpk9"},{"kid":"k8xdnqqxx76nm26x","sourceFid":"fzkrcuh3zzedhpk9","targetFid":"fwcmrnpbzehvs4s3"},{"kid":"kmgys75we4avq43s","sourceFid":"fwcmrnpbzehvs4s3","targetFid":"fpznmzcz9cn9dq9t"}],"preferences":{},"variables":{},"variableRef":[],"innerModels":{},"inData":[],"outData":[],"sheets":[],"param":{},"report":{"title":"Report","data":[]},"persist-mode":"auto","diagram":{"PAPER_MARGIN_TOP":20,"PAPER_MARGIN_LEFT":20,"FIGURE_WIDTH":195,"FIGURE_HEIGHT":60,"GAP_WIDTH":55,"GAP_HEIGHT":40},"problemList":[]},"description":"","model_image":null,"creator":"brightics@samsung.com","create_time":"2024-12-13T22:11:20.000Z","updater":"brightics@samsung.com","update_time":"2024-12-14T02:24:09.000Z","event_key":"2024_022409.000","type":"data","tag":"null","from_version":"0.0"}}],"version":"3.6"}